databricks/__init__.py
databricks/automl_runtime/__init__.py
databricks/automl_runtime/utils.py
databricks/automl_runtime/version.py
databricks/automl_runtime/forecast/__init__.py
databricks/automl_runtime/forecast/model.py
databricks/automl_runtime/forecast/utils.py
databricks/automl_runtime/forecast/pmdarima/__init__.py
databricks/automl_runtime/forecast/pmdarima/diagnostics.py
databricks/automl_runtime/forecast/pmdarima/model.py
databricks/automl_runtime/forecast/pmdarima/training.py
databricks/automl_runtime/forecast/pmdarima/utils.py
databricks/automl_runtime/forecast/prophet/__init__.py
databricks/automl_runtime/forecast/prophet/diagnostics.py
databricks/automl_runtime/forecast/prophet/forecast.py
databricks/automl_runtime/forecast/prophet/model.py
databricks/automl_runtime/hyperopt/__init__.py
databricks/automl_runtime/hyperopt/early_stop.py
databricks/automl_runtime/sklearn/__init__.py
databricks/automl_runtime/sklearn/base_datetime_transformer.py
databricks/automl_runtime/sklearn/column_selector.py
databricks/automl_runtime/sklearn/date_transformer.py
databricks/automl_runtime/sklearn/datetime_imputer.py
databricks/automl_runtime/sklearn/interpolation_imputer.py
databricks/automl_runtime/sklearn/one_hot_encoder.py
databricks/automl_runtime/sklearn/pandas_column_transformer.py
databricks/automl_runtime/sklearn/pandas_simple_imputer.py
databricks/automl_runtime/sklearn/pandas_transformer_wrapper.py
databricks/automl_runtime/sklearn/timestamp_transformer.py
databricks/automl_runtime/sklearn/transformed_target_classifier.py
databricks_automl_runtime-0.2.21.dist-info/METADATA
databricks_automl_runtime-0.2.21.dist-info/WHEEL
databricks_automl_runtime-0.2.21.dist-info/top_level.txt
databricks_automl_runtime-0.2.21.dist-info/RECORD
